{
  "$schema": "https://unpkg.com/@t8/docsgen/schema.json",
  "favicon": "/assets/icon.png",
  "append": {
    "head": "<link rel=\"stylesheet\" href=\"/assets/entry.css\">",
    "body": "<script src=\"/assets/stats.js\"></script>"
  },
  "firstLineDescription": true,
  "entries": [
    {
      "dir": "react-router",
      "htmlTitle": "<a href=\"/\">T8</a> React Router",
      "repo": "https://github.com/axcraft/react-router",
      "npm": "https://www.npmjs.com/package/@t8/react-router",
      "nav": "/assets/nav_react.html"
    },
    {
      "dir": "react-store",
      "htmlTitle": "<a href=\"/\">T8</a> React Store",
      "repo": "https://github.com/axcraft/react-store",
      "npm": "https://www.npmjs.com/package/@t8/react-store",
      "nav": "/assets/nav_react.html",
      "singlePage": true
    },
    {
      "dir": "react-pending",
      "htmlTitle": "<a href=\"/\">T8</a> React Pending",
      "repo": "https://github.com/axcraft/react-pending",
      "npm": "https://www.npmjs.com/package/@t8/react-pending",
      "nav": "/assets/nav_react.html",
      "singlePage": true
    },
    {
      "dir": "router",
      "htmlTitle": "<a href=\"/\">T8</a> Router",
      "repo": "https://github.com/axcraft/router",
      "npm": "https://www.npmjs.com/package/@t8/router",
      "nav": "/assets/nav_vanilla.html",
      "singlePage": true
    },
    {
      "dir": "store",
      "htmlTitle": "<a href=\"/\">T8</a> Store",
      "repo": "https://github.com/axcraft/store",
      "npm": "https://www.npmjs.com/package/@t8/store",
      "nav": "/assets/nav_vanilla.html",
      "singlePage": true
    },
    {
      "dir": "url-shape",
      "title": "URL Shape",
      "htmlTitle": "URL&nbsp;Shape&nbsp;<sup><a href=\"/\">T8</a></sup>",
      "repo": "https://github.com/axcraft/url-shape",
      "npm": "https://www.npmjs.com/package/url-shape",
      "nav": "/assets/nav_vanilla.html",
      "singlePage": true
    },
    {
      "dir": "sdk-factory",
      "htmlTitle": "<a href=\"/\">T8</a> SDK Factory",
      "repo": "https://github.com/axcraft/sdk-factory",
      "npm": "https://www.npmjs.com/package/@t8/sdk-factory",
      "nav": "/assets/nav_vanilla.html"
    }
  ],
  "linkMap": {
    "https://github.com/axcraft/react-store": "/react-store",
    "https://github.com/axcraft/react-store#readme": "/react-store",
    "https://github.com/axcraft/react-router": "/react-router",
    "https://github.com/axcraft/react-router#readme": "/react-router",
    "https://github.com/axcraft/react-pending": "/react-pending",
    "https://github.com/axcraft/react-pending#readme": "/react-pending",
    "https://github.com/axcraft/url-shape": "/url-shape",
    "https://github.com/axcraft/url-shape#readme": "/url-shape"
  }
}
